aztools/__init__.py
aztools/aztools.py
aztools/extract.py
goataztools-2024.7.16.1622.dist-info/METADATA
goataztools-2024.7.16.1622.dist-info/WHEEL
goataztools-2024.7.16.1622.dist-info/entry_points.txt
goataztools-2024.7.16.1622.dist-info/top_level.txt
goataztools-2024.7.16.1622.dist-info/RECORD
